terraclip/__init__.py
terraclip/core.py
terraclip-1.0b2.dist-info/METADATA
terraclip-1.0b2.dist-info/WHEEL
terraclip-1.0b2.dist-info/licenses/LICENSE
terraclip-1.0b2.dist-info/RECORD
