Metadata-Version: 2.1
Name: terraclip
Version: 1.0b2
Summary: Anti-collision Ardupilot terrain following mission generator.
Project-URL: Homepage, https://github.com/Rodrigo-NH/Terraclip
Project-URL: Bug Tracker, https://github.com/Rodrigo-NH/Terraclip/issues
Author-email: Rodrigo Nascimento Hernandez <rodrigomdev@gmail.com>
License-File: LICENSE
Classifier: Development Status :: 4 - Beta
Classifier: Framework :: IPython
Classifier: Intended Audience :: Developers
Classifier: License :: OSI Approved :: BSD License
Classifier: Operating System :: OS Independent
Classifier: Programming Language :: Python
Classifier: Topic :: Scientific/Engineering :: GIS
Requires-Python: >=3.1
Requires-Dist: certifi
Requires-Dist: gdalwrap
Requires-Dist: numpy
Requires-Dist: requests
